bugdantic/__init__.py
bugdantic/bugzilla.py
bugdantic/py.typed
bugdantic-0.2.6.dist-info/licenses/LICENSE
bugdantic-0.2.6.dist-info/METADATA
bugdantic-0.2.6.dist-info/WHEEL
bugdantic-0.2.6.dist-info/top_level.txt
bugdantic-0.2.6.dist-info/RECORD
